poorman/__about__.py
poorman/__init__.py
poorman-0.0.1.dist-info/METADATA
poorman-0.0.1.dist-info/WHEEL
poorman-0.0.1.dist-info/licenses/LICENSE.txt
poorman-0.0.1.dist-info/RECORD
